[{"FieldBlockID":1,"BlockChar":"A","FieldBlockYear":2017,"FieldBlockLength":300,"FieldBlockWidth":500,"Comment":"This is a field comment"},{"FieldBlockID":2,"BlockChar":"B","FieldBlockYear":2017,"FieldBlockLength":123,"FieldBlockWidth":321,"Comment":"This is a field comment"},{"FieldBlockID":3,"BlockChar":"C","FieldBlockYear":2017,"FieldBlockLength":123,"FieldBlockWidth":321,"Comment":"This is a field comment"},{"FieldBlockID":4,"BlockChar":"A","FieldBlockYear":2018,"FieldBlockLength":521,"FieldBlockWidth":145,"Comment":"This is a field comment"},{"FieldBlockID":5,"BlockChar":"B","FieldBlockYear":2018,"FieldBlockLength":654,"FieldBlockWidth":456,"Comment":"This is a field comment"},{"FieldBlockID":6,"BlockChar":"A","FieldBlockYear":2016,"FieldBlockLength":1254,"FieldBlockWidth":412,"Comment":"This is a field comment"},{"FieldBlockID":7,"BlockChar":"A","FieldBlockYear":2015,"FieldBlockLength":124,"FieldBlockWidth":452,"Comment":"This is a field comment"}]